LICENSE
MANIFEST.in
README.md
requirements.txt
setup.cfg
setup.py
etc/zonebot-example-config.cfg
test/test_commands.py
test/test_splitall.py
test/test_validate_config.py
test/test_zonebot.py
test/test_zoneminder.py
zonebot/__init__.py
zonebot/bot.py
zonebot/commands.py
zonebot/zonebot_alert.py
zonebot/zonebot_get_id.py
zonebot/zonebot_main.py
zonebot.egg-info/PKG-INFO
zonebot.egg-info/SOURCES.txt
zonebot.egg-info/dependency_links.txt
zonebot.egg-info/entry_points.txt
zonebot.egg-info/requires.txt
zonebot.egg-info/top_level.txt
zonebot/zoneminder/__init__.py
zonebot/zoneminder/monitors.py
zonebot/zoneminder/session.py
zonebot/zoneminder/zoneminder.py