Metadata-Version: 1.1
Name: zonebot
Version: 1.0
Summary: A Slack bot to interact with ZoneMinder
Home-page: https://github.com/rjclark/zoneminder-slack-bot
Author: Robert Clark
Author-email: clark@exiter.com
License: Apache
Keywords: slack,zoneminder
Platform: any
Classifier: Programming Language :: Python
Classifier: Development Status :: 2 - Pre-Alpha
Classifier: License :: OSI Approved :: Apache Software License
Classifier: Programming Language :: Python :: 2
Classifier: Programming Language :: Python :: 2.7
Classifier: Programming Language :: Python :: 3
Classifier: Programming Language :: Python :: 3.3
Classifier: Programming Language :: Python :: 3.4
Classifier: Programming Language :: Python :: 3.5
Classifier: Operating System :: OS Independent
Classifier: Topic :: Communications :: Chat
